torchradio/__init__.py
torchradio/device.py
torchradio/position.py
torchradio/types.py
torchradio/algorithm/__init__.py
torchradio/algorithm/example.py
torchradio/algorithm/modem.py
torchradio/algorithm/null.py
torchradio/algorithm/utils.py
torchradio/env/__init__.py
torchradio/env/base.py
torchradio/env/box.py
torchradio/env/null.py
torchradio-0.0.3.dist-info/METADATA
torchradio-0.0.3.dist-info/WHEEL
torchradio-0.0.3.dist-info/licenses/LICENSE
torchradio-0.0.3.dist-info/RECORD
