Metadata-Version: 2.3
Name: torchradio
Version: 0.0.3
Summary: A PyTorch differentiable RF simulation environment
Project-URL: Homepage, https://github.com/dewcservices/torchradio
Project-URL: Bug Tracker, https://github.com/dewcservices/torchradio/issues
Author-email: Daniel Gibbons <daniel.gibbons@dewc.com>
License-File: LICENSE
Classifier: License :: OSI Approved :: MIT License
Classifier: Operating System :: OS Independent
Classifier: Programming Language :: Python :: 3
Requires-Python: >=3.10
Requires-Dist: numpy
Requires-Dist: scikit-commpy
Requires-Dist: torch
Provides-Extra: dev
Requires-Dist: chart-studio; extra == 'dev'
Requires-Dist: coverage; extra == 'dev'
Requires-Dist: ipykernel; extra == 'dev'
Requires-Dist: ipywidgets; extra == 'dev'
Requires-Dist: kaleido; extra == 'dev'
Requires-Dist: matplotlib; extra == 'dev'
Requires-Dist: mkdocs; extra == 'dev'
Requires-Dist: mkdocs-jupyter; extra == 'dev'
Requires-Dist: mkdocs-material; extra == 'dev'
Requires-Dist: mkdocstrings[python]; extra == 'dev'
Requires-Dist: mknotebooks; extra == 'dev'
Requires-Dist: mypy; extra == 'dev'
Requires-Dist: pandas; extra == 'dev'
Requires-Dist: pre-commit; extra == 'dev'
Requires-Dist: pymdown-extensions; extra == 'dev'
Requires-Dist: pytest; extra == 'dev'
Requires-Dist: ruff; extra == 'dev'
Requires-Dist: tqdm; extra == 'dev'
Requires-Dist: types-tqdm; extra == 'dev'
Requires-Dist: widgetsnbextension; extra == 'dev'
Provides-Extra: docs
Requires-Dist: mkdocs; extra == 'docs'
Requires-Dist: mkdocs-jupyter; extra == 'docs'
Requires-Dist: mkdocs-material; extra == 'docs'
Requires-Dist: mkdocstrings[python]; extra == 'docs'
Requires-Dist: mknotebooks; extra == 'docs'
Requires-Dist: pymdown-extensions; extra == 'docs'
Provides-Extra: notebooks
Requires-Dist: chart-studio; extra == 'notebooks'
Requires-Dist: ipykernel; extra == 'notebooks'
Requires-Dist: ipywidgets; extra == 'notebooks'
Requires-Dist: kaleido; extra == 'notebooks'
Requires-Dist: matplotlib; extra == 'notebooks'
Requires-Dist: pandas; extra == 'notebooks'
Requires-Dist: tqdm; extra == 'notebooks'
Requires-Dist: widgetsnbextension; extra == 'notebooks'
